yoga/version.py
yoga/__init__.py
yoga/cli.py
yoga/__main__.py
yoga/image/options.py
yoga/image/__init__.py
yoga/image/cli.py
yoga/image/helpers.py
yoga/image/encoders/webp.py
yoga/image/encoders/jpeg.py
yoga/image/encoders/__init__.py
yoga/image/encoders/png.py
yoga/image/encoders/webp_lossless.py
yoga/model/_assimp.cpython-314t-darwin.so
yoga/model/options.py
yoga/model/__init__.py
yoga/model/cli.py
yoga/model/assimp.py
yoga/model/assimp_build.py
yoga/model/helpers.py
yoga-1.3.4.dist-info/RECORD
yoga-1.3.4.dist-info/WHEEL
yoga-1.3.4.dist-info/entry_points.txt
yoga-1.3.4.dist-info/top_level.txt
yoga-1.3.4.dist-info/METADATA
yoga-1.3.4.dist-info/licenses/LICENSE
