Metadata-Version: 2.1
Name: yoga
Version: 1.3.4
Summary: Yummy Optimizer for Gorgeous Assets
Home-page: https://github.com/wanadev/yoga
Author: Wanadev
Author-email: contact@wanadev.fr
Maintainer: Fabien LOISON, Alexis BREUST
License: BSD-3-Clause
Project-URL: Source Code, https://github.com/wanadev/yoga
Project-URL: Documentation, https://wanadev.github.io/yoga/
Project-URL: Changelog, https://github.com/wanadev/yoga#changelog
Project-URL: Issues, https://github.com/wanadev/yoga/issues
Project-URL: Chat, https://discord.gg/BmUkEdMuFp
Keywords: image webp jpeg png optimizer guetzli zopfli zopflipng libwebp 3d model mesh assimp gltf glb converter
License-File: LICENSE
Requires-Dist: cffi >=1.0.0
Requires-Dist: imagequant >=1.0.2
Requires-Dist: mozjpeg-lossless-optimization >=1.0.0
Requires-Dist: pillow >=6.2.2
Requires-Dist: pyguetzli >=1.0.0
Requires-Dist: unidecode >=1.0.0
Requires-Dist: zopflipy >=1.0
Provides-Extra: dev
Requires-Dist: nox ; extra == 'dev'
Requires-Dist: flake8 ; extra == 'dev'
Requires-Dist: black ; extra == 'dev'
Requires-Dist: pytest ; extra == 'dev'
Requires-Dist: sphinx ; extra == 'dev'
Requires-Dist: sphinx-rtd-theme ; extra == 'dev'
Requires-Dist: codespell ; extra == 'dev'
